iva2k_how_long/__init__.py
iva2k_how_long/how_long.py
iva2k_how_long-0.1.4.dist-info/WHEEL
iva2k_how_long-0.1.4.dist-info/METADATA
iva2k_how_long-0.1.4.dist-info/RECORD
