Metadata-Version: 2.1
Name: iva2k-how-long
Version: 0.1.4
Summary: A simple decorator to measure a function excecution time.
License: MIT
Author: iva2k
Author-email: iva2k@yahoo.com
Requires-Python: >=3.7,<4.0
Classifier: License :: OSI Approved :: MIT License
Classifier: Programming Language :: Python :: 3
Classifier: Programming Language :: Python :: 3.7
Classifier: Programming Language :: Python :: 3.8
Classifier: Programming Language :: Python :: 3.9
Requires-Dist: pendulum (>=2.1.2,<3.0.0)
